xchembku_api/__init__.py
xchembku_api/aiohttp_client.py
xchembku_api/exceptions.py
xchembku_api/crystal_plate_objects/__init__.py
xchembku_api/crystal_plate_objects/constants.py
xchembku_api/crystal_plate_objects/interface.py
xchembku_api/databases/__init__.py
xchembku_api/databases/constants.py
xchembku_api/databases/database_definition.py
xchembku_api/databases/table_definitions.py
xchembku_api/datafaces/__init__.py
xchembku_api/datafaces/aiohttp.py
xchembku_api/datafaces/constants.py
xchembku_api/datafaces/context.py
xchembku_api/datafaces/datafaces.py
xchembku_api/models/crystal_plate_filter_model.py
xchembku_api/models/crystal_plate_model.py
xchembku_api/models/crystal_plate_report_model.py
xchembku_api/models/crystal_well_autolocation_model.py
xchembku_api/models/crystal_well_droplocation_model.py
xchembku_api/models/crystal_well_filter_model.py
xchembku_api/models/crystal_well_model.py
xchembku_api/models/crystal_well_needing_droplocation_model.py
xchembku_cli/__init__.py
xchembku_cli/main.py
xchembku_cli/version.py
xchembku_cli/subcommands/__init__.py
xchembku_cli/subcommands/base.py
xchembku_cli/subcommands/service.py
xchembku_lib/__init__.py
xchembku_lib/__main__.py
xchembku_lib/_version.py
xchembku_lib/base_aiohttp.py
xchembku_lib/envvar.py
xchembku_lib/version.py
xchembku_lib/crystal_plate_objects/crystal_plate_objects.py
xchembku_lib/crystal_plate_objects/swiss3.py
xchembku_lib/datafaces/__init__.py
xchembku_lib/datafaces/aiohttp.py
xchembku_lib/datafaces/context.py
xchembku_lib/datafaces/datafaces.py
xchembku_lib/datafaces/direct.py
xchembku_lib/datafaces/direct_base.py
xchembku_lib/datafaces/direct_crystal_plates.py
xchembku_lib/datafaces/direct_crystal_well_autolocations.py
xchembku_lib/datafaces/direct_crystal_well_droplocations.py
xchembku_lib/datafaces/direct_crystal_wells.py
xchembku_lib/datafaces/direct_soakdb3_crystal_wells.py
xchembku-1.10.3.dist-info/LICENSE
xchembku-1.10.3.dist-info/METADATA
xchembku-1.10.3.dist-info/WHEEL
xchembku-1.10.3.dist-info/entry_points.txt
xchembku-1.10.3.dist-info/top_level.txt
xchembku-1.10.3.dist-info/RECORD
